Stabdifspy/__init__.py
Stabdifspy/Generator/Stab.py
Stabdifspy/Library/Prompter.py
Stabdifspy/Library/StabdifspyConfig.py
Stabdifspy/Library/StabdifspyConfiger.py
Stabdifspy/Library/StabdifspyDeclare.py
Stabdifspy/Library/StabdifspyException.py
Stabdifspy/Library/StabdifspyGlobals.py
Stabdifspy-1.0.14.dist-info/METADATA
Stabdifspy-1.0.14.dist-info/WHEEL
Stabdifspy-1.0.14.dist-info/top_level.txt
Stabdifspy-1.0.14.dist-info/RECORD
