Metadata-Version: 2.1
Name: Stabdifspy
Version: 1.0.14
Summary: AIPicture generator
Home-page: https://github.com/kaioman/Stabdifspy.git
Author: unchainworks
Author-email: kajin0318@gmail.com
License: BSD-3-Clause
Keywords: AI,Picutre,Generator
Platform: UNKNOWN
Classifier: Development Status :: 5 - Production/Stable
Classifier: License :: OSI Approved :: BSD License
Classifier: Programming Language :: Python
Classifier: Programming Language :: Python :: 3
Classifier: Programming Language :: Python :: 3.4
Classifier: Programming Language :: Python :: 3.5
Classifier: Programming Language :: Python :: 3.6
Classifier: Programming Language :: Python :: 3.7
Classifier: Programming Language :: Python :: 3.8
Classifier: Programming Language :: Python :: 3.9
Classifier: Topic :: Database
Classifier: Topic :: Software Development :: Libraries :: Python Modules
Requires-Dist: certifi ==2023.11.17
Requires-Dist: charset-normalizer ==3.3.2
Requires-Dist: docutils ==0.20.1
Requires-Dist: et-xmlfile ==1.1.0
Requires-Dist: greenlet ==3.0.1
Requires-Dist: idna ==3.6
Requires-Dist: importlib-metadata ==7.0.0
Requires-Dist: jaraco.classes ==3.3.0
Requires-Dist: keyring ==24.3.0
Requires-Dist: LibHanger ==1.0.80
Requires-Dist: lxml ==4.9.1
Requires-Dist: markdown-it-py ==3.0.0
Requires-Dist: mdurl ==0.1.2
Requires-Dist: more-itertools ==10.1.0
Requires-Dist: nh3 ==0.2.15
Requires-Dist: numpy ==1.26.2
Requires-Dist: openpyxl ==3.0.10
Requires-Dist: pandas ==1.5.1
Requires-Dist: Pillow ==9.3.0
Requires-Dist: pkginfo ==1.9.6
Requires-Dist: psutil ==5.9.4
Requires-Dist: psycopg2 ==2.9.5
Requires-Dist: Pygments ==2.17.2
Requires-Dist: python-dateutil ==2.8.2
Requires-Dist: pytz ==2023.3.post1
Requires-Dist: pywin32-ctypes ==0.2.2
Requires-Dist: readme-renderer ==42.0
Requires-Dist: requests ==2.31.0
Requires-Dist: requests-toolbelt ==1.0.0
Requires-Dist: rfc3986 ==2.0.0
Requires-Dist: rich ==13.7.0
Requires-Dist: Scrapinger ==1.0.37
Requires-Dist: selenium ==3.141.0
Requires-Dist: six ==1.16.0
Requires-Dist: soupsieve ==2.3.2.post1
Requires-Dist: SQLAlchemy ==1.4.44
Requires-Dist: twine ==4.0.2
Requires-Dist: typing-extensions ==4.5.0
Requires-Dist: tzdata ==2023.3
Requires-Dist: urllib3 ==2.1.0
Requires-Dist: webencodings ==0.5.1
Requires-Dist: xlrd ==2.0.1
Requires-Dist: zipp ==3.17.0
